llm_testkit/__init__.py
llm_testkit/cli.py
llm_testkit/main.py
llm_testkit/evaluation/__init__.py
llm_testkit/evaluation/evaluator.py
llm_testkit/models/__init__.py
llm_testkit/models/model_config.py
llm_testkit/normalization/__init__.py
llm_testkit/normalization/score_normalizer.py
llm_testkit/reporting/__init__.py
llm_testkit/reporting/html_report_generator.py
llm_testkit/reporting/professional_report_generator.py
llm_testkit/reporting/report_generator.py
llm_testkit/tasks/__init__.py
llm_testkit/tasks/task_config.py
llm_testkit/utils/__init__.py
llm_testkit/utils/gpu.py
llm_testkit/utils/json_utils.py
llm_testkit-1.1.1.dist-info/licenses/LICENSE
llm_testkit-1.1.1.dist-info/METADATA
llm_testkit-1.1.1.dist-info/WHEEL
llm_testkit-1.1.1.dist-info/entry_points.txt
llm_testkit-1.1.1.dist-info/top_level.txt
llm_testkit-1.1.1.dist-info/RECORD
