Metadata-Version: 2.4
Name: llm-testkit
Version: 1.1.1
Summary: Professional-grade LLM evaluation framework with ZENO-style HTML reports and enhanced sample analysis
Author-email: Matthias De Paolis <mattdepaolis@users.noreply.github.com>
License: MIT
Project-URL: Homepage, https://github.com/mattdepaolis/llm-eval
Project-URL: Bug Tracker, https://github.com/mattdepaolis/llm-eval/issues
Project-URL: Documentation, https://github.com/mattdepaolis/llm-eval#readme
Project-URL: Source Code, https://github.com/mattdepaolis/llm-eval
Classifier: Development Status :: 4 - Beta
Classifier: Intended Audience :: Developers
Classifier: Intended Audience :: Science/Research
Classifier: License :: OSI Approved :: MIT License
Classifier: Operating System :: OS Independent
Classifier: Programming Language :: Python :: 3
Classifier: Programming Language :: Python :: 3.8
Classifier: Programming Language :: Python :: 3.9
Classifier: Programming Language :: Python :: 3.10
Classifier: Programming Language :: Python :: 3.11
Classifier: Programming Language :: Python :: 3.12
Classifier: Topic :: Scientific/Engineering :: Artificial Intelligence
Classifier: Topic :: Software Development :: Libraries :: Python Modules
Requires-Python: >=3.8
License-File: LICENSE
Requires-Dist: torch>=2.7.0
Requires-Dist: transformers>=4.20.0
Requires-Dist: numpy>=1.21.0
Requires-Dist: pandas>=1.3.0
Requires-Dist: tqdm>=4.62.0
Requires-Dist: matplotlib>=3.4.0
Requires-Dist: seaborn>=0.11.0
Requires-Dist: datasets>=2.0.0
Requires-Dist: accelerate>=0.12.0
Requires-Dist: sacrebleu>=2.0.0
Requires-Dist: sqlitedict>=2.0.0
Requires-Dist: lm-eval>=0.4.0
Provides-Extra: dev
Requires-Dist: pytest>=6.0; extra == "dev"
Requires-Dist: pytest-cov>=2.0; extra == "dev"
Requires-Dist: black>=21.0; extra == "dev"
Requires-Dist: flake8>=3.8; extra == "dev"
Requires-Dist: isort>=5.0; extra == "dev"
Provides-Extra: cuda128
Requires-Dist: torch>=2.7.0; platform_system != "Darwin" and extra == "cuda128"
Requires-Dist: torchvision>=0.19.0; platform_system != "Darwin" and extra == "cuda128"
Requires-Dist: torchaudio>=2.4.0; platform_system != "Darwin" and extra == "cuda128"
Provides-Extra: cuda
Requires-Dist: torch>=2.7.0; extra == "cuda"
Requires-Dist: torchvision>=0.19.0; extra == "cuda"
Requires-Dist: torchaudio>=2.4.0; extra == "cuda"
Dynamic: license-file
